omotes_job_tools/__init__.py
omotes_job_tools/app_logging.py
omotes_job_tools/broker_interface.py
omotes_job_tools/config.py
omotes_job_tools/job.py
omotes_job_tools/messages.py
omotes_job_tools/workflow_type.py
omotes_job_tools-0.0.1.dist-info/LICENSE
omotes_job_tools-0.0.1.dist-info/METADATA
omotes_job_tools-0.0.1.dist-info/WHEEL
omotes_job_tools-0.0.1.dist-info/top_level.txt
omotes_job_tools-0.0.1.dist-info/RECORD
